<?xml version="1.0" encoding="UTF-8"?>

<datamodel name="QoS" version="2.0">
	<object name="QoS." access="readOnly" minEntries="1" maxEntries="1" set="QoSDefault.sh">
		<parameter name="AppNumberOfEntries" access="readOnly" store="no">
			<syntax>
				<unsignedInt />
				<default value="0" />
			</syntax>
		</parameter>
		<parameter name="AvailableAppList" access="readOnly" supported="no">
			<syntax>
				<list>
					<size minLength="0" maxLength="1024" />
				</list>
				<string />
			</syntax>
		</parameter>
		<parameter name="ClassificationNumberOfEntries" access="readOnly" store="no">
			<syntax>
				<unsignedInt />
				<default value="0" />
			</syntax>
		</parameter>
		<parameter name="DefaultDSCPMark" access="readWrite">
			<syntax>
				<int>
					<range minInclusive="-2" maxInclusive="63" step="1" />
				</int>
			</syntax>
		</parameter>
		<parameter name="DefaultEthernetPriorityMark" access="readWrite">
			<syntax>
				<int>
					<range minInclusive="-2" maxInclusive="7" step="1" />
				</int>
			</syntax>
		</parameter>
		<parameter name="DefaultForwardingPolicy" access="readWrite">
			<syntax>
				<unsignedInt />
			</syntax>
		</parameter>
		<parameter name="DefaultPolicer" access="readWrite">
			<syntax>
				<string>
					<size minLength="0" maxLength="256" />
					<pathRef targetParent="Policer." refType="strong" targetType="row" />
				</string>
				<default value="" />
			</syntax>
		</parameter>
		<parameter name="DefaultQueue" access="readWrite" get="QoSQueueDflt.sh">
			<syntax>
				<string>
					<size minLength="0" maxLength="256" />
					<pathRef targetParent="Queue." refType="strong" targetType="row" />
				</string>
				<default value="" />
			</syntax>
		</parameter>
		<parameter name="DefaultTrafficClass" access="readWrite">
			<syntax>
				<unsignedInt />
			</syntax>
		</parameter>
		<parameter name="FlowNumberOfEntries" access="readOnly" store="no">
			<syntax>
				<unsignedInt />
				<default value="0" />
			</syntax>
		</parameter>
		<parameter name="MaxAppEntries" access="readOnly" activeNotify="canDeny">
			<syntax>
				<unsignedInt />
			</syntax>
		</parameter>
		<parameter name="MaxClassificationEntries" access="readOnly" activeNotify="canDeny">
			<syntax>
				<unsignedInt />
			</syntax>
		</parameter>
		<parameter name="MaxFlowEntries" access="readOnly" activeNotify="canDeny">
			<syntax>
				<unsignedInt />
			</syntax>
		</parameter>
		<parameter name="MaxPolicerEntries" access="readOnly" activeNotify="canDeny">
			<syntax>
				<unsignedInt />
			</syntax>
		</parameter>
		<parameter name="MaxQueueEntries" access="readOnly" activeNotify="canDeny">
			<syntax>
				<unsignedInt />
			</syntax>
		</parameter>
		<parameter name="MaxShaperEntries" access="readOnly" activeNotify="canDeny">
			<syntax>
				<unsignedInt />
			</syntax>
		</parameter>
		<parameter name="PolicerNumberOfEntries" access="readOnly" store="no">
			<syntax>
				<unsignedInt />
				<default value="0" />
			</syntax>
		</parameter>
		<parameter name="QueueNumberOfEntries" access="readOnly" store="no">
			<syntax>
				<unsignedInt />
				<default value="0" />
			</syntax>
		</parameter>
		<parameter name="QueueStatsNumberOfEntries" access="readOnly" store="no">
			<syntax>
				<unsignedInt />
				<default value="0" />
			</syntax>
		</parameter>
		<parameter name="IngressShaperNumberOfEntries" access="readOnly" store="no">
			<syntax>
				<unsignedInt />
				<default value="0" />
			</syntax>
		</parameter>
		<parameter name="ShaperNumberOfEntries" access="readOnly" store="no">
			<syntax>
				<unsignedInt />
				<default value="0" />
			</syntax>
		</parameter>
	</object>
	<object name="QoS.App.{i}." access="readWrite" minEntries="0" maxEntries="unbounded" numEntriesParameter="AppNumberOfEntries" enableParameter="Enable" set="QoSApp.sh" del="QoSApp.sh">
		<parameter name="Alias" access="readWrite" key="yes">
			<syntax>
				<dataType ref="Alias" />
			</syntax>
		</parameter>
		<parameter name="DefaultDSCPMark" access="readWrite">
			<syntax>
				<int>
					<range minInclusive="-2" maxInclusive="63" step="1" />
				</int>
				<default value="-1" />
			</syntax>
		</parameter>
		<parameter name="DefaultEthernetPriorityMark" access="readWrite">
			<syntax>
				<int>
					<range minInclusive="-2" maxInclusive="7" step="1" />
				</int>
				<default value="-1" />
			</syntax>
		</parameter>
		<parameter name="DefaultForwardingPolicy" access="readWrite">
			<syntax>
				<unsignedInt />
				<default value="0" />
			</syntax>
		</parameter>
		<parameter name="DefaultPolicer" access="readWrite">
			<syntax>
				<string>
					<size minLength="0" maxLength="256" />
					<pathRef targetParent="#.Policer." refType="strong" targetType="row" />
				</string>
				<default value="" />
			</syntax>
		</parameter>
		<parameter name="DefaultTrafficClass" access="readWrite">
			<syntax>
				<unsignedInt />
				<default value="0" />
			</syntax>
		</parameter>
		<parameter name="Enable" access="readWrite">
			<syntax>
				<boolean />
				<default value="false" />
			</syntax>
		</parameter>
		<parameter name="Name" access="readWrite">
			<syntax>
				<dataType ref="Name" />
			</syntax>
		</parameter>
		<parameter name="ProtocolIdentifier" access="readWrite">
			<syntax>
				<string>
					<size minLength="0" maxLength="256" />
				</string>
				<default value="" />
			</syntax>
		</parameter>
		<parameter name="Status" access="readOnly" store="no">
			<syntax>
				<string>
					<enumeration value="Disabled" />
					<enumeration value="Enabled" />
					<enumeration value="Error" />
				</string>
				<default value="Disabled" />
			</syntax>
		</parameter>
		<parameter name="X_ADB_Permissions" access="readWrite">
			<syntax>
				<dataType ref="UserPermission" />
				<default value="333" />
			</syntax>
		</parameter>
	</object>
	<object name="QoS.X_ADB_DefaultClassification." access="readWrite" minEntries="1" maxEntries="1" set="QoSControlClassification.sh">
		<parameter name="Enable" access="readWrite">
			<syntax>
				<boolean />
				<default value="false" />
			</syntax>
		</parameter>
		<parameter name="Queue" access="readWrite">
			<syntax>
				<string>
					<size minLength="0" maxLength="256" />
				</string>
				<default value="" />
			</syntax>
		</parameter>
		<parameter name="TrafficClass" access="readOnly">
			<syntax>
				<unsignedInt />
				<default value="0" />
			</syntax>
		</parameter>
		<parameter name="Protocols" access="readWrite">
			<syntax>
				<string>
					<size minLength="0" maxLength="256" />
				</string>
				<default value="ARP,DHCP,IGMP,PPPoE" />
			</syntax>
		</parameter>
		<parameter name="Status" access="readOnly" store="no">
			<syntax>
				<string>
					<enumeration value="Disabled" />
					<enumeration value="Enabled" />
				</string>
				<default value="Disabled" />
			</syntax>
		</parameter>
	</object>
	<object name="QoS.Classification.{i}." access="readWrite" minEntries="0" maxEntries="unbounded" numEntriesParameter="ClassificationNumberOfEntries" enableParameter="Enable" set="QoSClassification.sh" add="QoSClassification.sh" del="QoSClassification.sh">
		<parameter name="Enable" access="readWrite">
			<syntax>
				<boolean />
				<default value="false" />
			</syntax>
		</parameter>
		<parameter name="Order" access="readWrite">
			<syntax>
				<unsignedInt>
					<range minInclusive="1" step="1" />
				</unsignedInt>
			</syntax>
		</parameter>
		<parameter name="Alias" access="readWrite" key="yes">
			<syntax>
				<dataType ref="Alias" />
			</syntax>
		</parameter>
		<parameter name="AllInterfaces" access="readWrite">
			<syntax>
				<boolean />
				<default value="false" />
			</syntax>
		</parameter>
		<parameter name="App" access="readWrite">
			<syntax>
				<string>
					<size minLength="0" maxLength="256" />
					<pathRef targetParent="#.App." refType="strong" targetType="row" />
				</string>
				<default value="" />
			</syntax>
		</parameter>
		<parameter name="DHCPType" access="readWrite" supported="no">
			<syntax>
				<string>
					<enumeration value="DHCPv4" />
					<enumeration value="DHCPv6" />
				</string>
				<default value="DHCPv4" />
			</syntax>
		</parameter>
		<parameter name="DSAP" access="readWrite">
			<syntax>
				<int>
					<range minInclusive="-1" step="1" />
				</int>
				<default value="-1" />
			</syntax>
		</parameter>
		<parameter name="DSAPExclude" access="readWrite">
			<syntax>
				<boolean />
				<default value="false" />
			</syntax>
		</parameter>
		<parameter name="DSCPCheck" access="readWrite">
			<syntax>
				<int>
					<range minInclusive="-1" step="1" />
				</int>
				<default value="-1" />
			</syntax>
		</parameter>
		<parameter name="DSCPExclude" access="readWrite">
			<syntax>
				<boolean />
				<default value="false" />
			</syntax>
		</parameter>
		<parameter name="DSCPMark" access="readWrite">
			<syntax>
				<int>
					<range minInclusive="-2" step="1" />
				</int>
				<default value="-1" />
			</syntax>
		</parameter>
		<parameter name="DestClientID" access="readWrite">
			<syntax>
				<default value="" />
			</syntax>
		</parameter>
		<parameter name="DestClientIDExclude" access="readWrite">
			<syntax>
				<boolean />
				<default value="false" />
			</syntax>
		</parameter>
		<parameter name="DestIP" access="readWrite">
			<syntax>
				<dataType ref="IPAddress" />
				<default value="" />
			</syntax>
		</parameter>
		<parameter name="DestIPExclude" access="readWrite">
			<syntax>
				<boolean />
				<default value="false" />
			</syntax>
		</parameter>
		<parameter name="DestMACAddress" access="readWrite">
			<syntax>
				<default value="" />
				<string>
					<size minLength="0" maxLength="17" />
					<pattern value="" />
					<pattern value="([0-9A-Fa-f][0-9A-Fa-f]:){5}([0-9A-Fa-f][0-9A-Fa-f])" />
				</string>
			</syntax>
		</parameter>
		<parameter name="DestMACExclude" access="readWrite">
			<syntax>
				<boolean />
				<default value="false" />
			</syntax>
		</parameter>
		<parameter name="DestMACMask" access="readWrite">
			<syntax>
				<default value="" />
				<string>
					<size minLength="0" maxLength="17" />
					<pattern value="" />
					<pattern value="([0-9A-Fa-f][0-9A-Fa-f]:){5}([0-9A-Fa-f][0-9A-Fa-f])" />
				</string>
			</syntax>
		</parameter>
		<parameter name="DestMask" access="readWrite">
			<syntax>
				<default value="" />
			</syntax>
		</parameter>
		<parameter name="DestPort" access="readWrite">
			<syntax>
				<int>
					<range minInclusive="-1" maxInclusive="65535" step="1" />
				</int>
				<default value="-1" />
			</syntax>
		</parameter>
		<parameter name="DestPortExclude" access="readWrite">
			<syntax>
				<boolean />
				<default value="false" />
			</syntax>
		</parameter>
		<parameter name="DestPortRangeMax" access="readWrite">
			<syntax>
				<int>
					<range minInclusive="-1" maxInclusive="65535" step="1" />
				</int>
				<default value="-1" />
			</syntax>
		</parameter>
		<parameter name="DestUserClassID" access="readWrite">
			<syntax>
				<default value="" />
			</syntax>
		</parameter>
		<parameter name="DestUserClassIDExclude" access="readWrite">
			<syntax>
				<boolean />
				<default value="false" />
			</syntax>
		</parameter>
		<parameter name="DestVendorClassID" access="readWrite">
			<syntax>
				<string>
					<size minLength="0" maxLength="255" />
				</string>
				<default value="" />
			</syntax>
		</parameter>
		<parameter name="DestVendorClassIDExclude" access="readWrite">
			<syntax>
				<boolean />
				<default value="false" />
			</syntax>
		</parameter>
		<parameter name="DestVendorClassIDMode" access="readWrite">
			<syntax>
				<string>
					<enumeration value="Exact" />
					<enumeration value="Prefix" />
					<enumeration value="Suffix" />
					<enumeration value="Substring" />
				</string>
				<default value="Exact" />
			</syntax>
		</parameter>
		<parameter name="DestVendorClassIDv6" access="readWrite" supported="no">
			<syntax>
				<default value="" />
			</syntax>
		</parameter>
		<parameter name="DestVendorSpecificInfo" access="readWrite" supported="no">
			<syntax>
				<default value="" />
			</syntax>
		</parameter>
		<parameter name="DestVendorSpecificInfoEnterprise" access="readWrite" supported="no">
			<syntax>
				<unsignedInt />
				<default value="0" />
			</syntax>
		</parameter>
		<parameter name="DestVendorSpecificInfoExclude" access="readWrite" supported="no">
			<syntax>
				<boolean />
				<default value="false" />
			</syntax>
		</parameter>
		<parameter name="DestVendorSpecificInfoSubOption" access="readWrite" supported="no">
			<syntax>
				<int>
					<range minInclusive="0" maxInclusive="255" step="1" />
				</int>
				<default value="0" />
			</syntax>
		</parameter>
		<parameter name="EthernetPriorityCheck" access="readWrite">
			<syntax>
				<int>
					<range minInclusive="-1" step="1" />
				</int>
				<default value="-1" />
			</syntax>
		</parameter>
		<parameter name="EthernetPriorityExclude" access="readWrite">
			<syntax>
				<boolean />
				<default value="false" />
			</syntax>
		</parameter>
		<parameter name="EthernetPriorityMark" access="readWrite">
			<syntax>
				<int>
					<range minInclusive="-2" step="1" />
				</int>
				<default value="-1" />
			</syntax>
		</parameter>
		<parameter name="Ethertype" access="readWrite">
			<syntax>
				<int>
					<range minInclusive="-1" step="1" />
				</int>
				<default value="-1" />
			</syntax>
		</parameter>
		<parameter name="EthertypeExclude" access="readWrite">
			<syntax>
				<boolean />
				<default value="false" />
			</syntax>
		</parameter>
		<parameter name="ForwardingPolicy" access="readWrite">
			<syntax>
				<unsignedInt />
				<default value="0" />
			</syntax>
		</parameter>
		<parameter name="X_ADB_ForwardingPolicyMask" access="readWrite">
			<syntax>
				<unsignedInt>
					<range minInclusive="0" maxInclusive="255" step="1" />
				</unsignedInt>
				<default value="255" />
			</syntax>
		</parameter>
		<parameter name="IPLengthExclude" access="readWrite">
			<syntax>
				<boolean />
				<default value="false" />
			</syntax>
		</parameter>
		<parameter name="IPLengthMax" access="readWrite">
			<syntax>
				<unsignedInt />
				<default value="0" />
			</syntax>
		</parameter>
		<parameter name="IPLengthMin" access="readWrite">
			<syntax>
				<unsignedInt />
				<default value="0" />
			</syntax>
		</parameter>
		<parameter name="X_ADB_Cascade" access="readWrite">
			<syntax>
				<boolean />
				<default value="false" />
			</syntax>
		</parameter>
		<parameter name="Interface" access="readWrite">
			<syntax>
				<string>
					<size minLength="0" maxLength="256" />
					<pathRef refType="strong" targetType="row" />
					<enumeration value="X_ADB_Local" />
				</string>
				<default value="" />
			</syntax>
		</parameter>
		<parameter name="X_ADB_InterfaceType" access="readWrite">
			<syntax>
				<string>
					<enumeration value="Ingress" />
					<enumeration value="Egress" />
				</string>
				<default value="Ingress" />
			</syntax>
		</parameter>
		<parameter name="LLCControl" access="readWrite">
			<syntax>
				<int>
					<range minInclusive="-1" step="1" />
				</int>
				<default value="-1" />
			</syntax>
		</parameter>
		<parameter name="LLCControlExclude" access="readWrite">
			<syntax>
				<boolean />
				<default value="false" />
			</syntax>
		</parameter>
		<parameter name="OutOfBandInfo" access="readWrite" supported="no">
			<syntax>
				<int>
					<range minInclusive="-1" step="1" />
				</int>
				<default value="-1" />
			</syntax>
		</parameter>
		<parameter name="Policer" access="readWrite">
			<syntax>
				<string>
					<size minLength="0" maxLength="256" />
					<pathRef targetParent="#.Policer." refType="strong" targetType="row" />
				</string>
				<default value="" />
			</syntax>
		</parameter>
		<parameter name="Protocol" access="readWrite">
			<syntax>
				<int>
					<range minInclusive="-1" step="1" />
				</int>
				<default value="-1" />
			</syntax>
		</parameter>
		<parameter name="ProtocolExclude" access="readWrite">
			<syntax>
				<boolean />
				<default value="false" />
			</syntax>
		</parameter>
		<parameter name="SNAPOUI" access="readWrite">
			<syntax>
				<int>
					<range minInclusive="-1" step="1" />
				</int>
				<default value="-1" />
			</syntax>
		</parameter>
		<parameter name="SNAPOUIExclude" access="readWrite">
			<syntax>
				<boolean />
				<default value="false" />
			</syntax>
		</parameter>
		<parameter name="SSAP" access="readWrite">
			<syntax>
				<int>
					<range minInclusive="-1" step="1" />
				</int>
				<default value="-1" />
			</syntax>
		</parameter>
		<parameter name="SSAPExclude" access="readWrite">
			<syntax>
				<boolean />
				<default value="false" />
			</syntax>
		</parameter>
		<parameter name="SourceClientID" access="readWrite">
			<syntax>
				<default value="" />
			</syntax>
		</parameter>
		<parameter name="SourceClientIDExclude" access="readWrite">
			<syntax>
				<boolean />
				<default value="false" />
			</syntax>
		</parameter>
		<parameter name="SourceIP" access="readWrite">
			<syntax>
				<list />
				<dataType ref="IPAddress" />
				<default value="" />
			</syntax>
		</parameter>
		<parameter name="SourceIPExclude" access="readWrite">
			<syntax>
				<boolean />
				<default value="false" />
			</syntax>
		</parameter>
		<parameter name="SourceMACAddress" access="readWrite">
			<syntax>
				<list />
				<string>
					<size minLength="0" maxLength="17" />
					<pattern value="" />
					<pattern value="([0-9A-Fa-f][0-9A-Fa-f]:){5}([0-9A-Fa-f][0-9A-Fa-f])" />
				</string>
				<default value="" />
			</syntax>
		</parameter>
		<parameter name="SourceMACExclude" access="readWrite">
			<syntax>
				<boolean />
				<default value="false" />
			</syntax>
		</parameter>
		<parameter name="SourceMACMask" access="readWrite">
			<syntax>
				<list />
				<default value="" />
				<string>
					<size minLength="0" maxLength="17" />
					<pattern value="" />
					<pattern value="([0-9A-Fa-f][0-9A-Fa-f]:){5}([0-9A-Fa-f][0-9A-Fa-f])" />
				</string>
			</syntax>
		</parameter>
		<parameter name="SourceMask" access="readWrite">
			<syntax>
				<list />
				<default value="" />
			</syntax>
		</parameter>
		<parameter name="SourcePort" access="readWrite">
			<syntax>
				<int>
					<range minInclusive="-1" maxInclusive="65535" step="1" />
				</int>
				<default value="-1" />
			</syntax>
		</parameter>
		<parameter name="SourcePortExclude" access="readWrite">
			<syntax>
				<boolean />
				<default value="false" />
			</syntax>
		</parameter>
		<parameter name="SourcePortRangeMax" access="readWrite">
			<syntax>
				<int>
					<range minInclusive="-1" maxInclusive="65535" step="1" />
				</int>
				<default value="-1" />
			</syntax>
		</parameter>
		<parameter name="SourceUserClassID" access="readWrite">
			<syntax>
				<default value="" />
			</syntax>
		</parameter>
		<parameter name="SourceUserClassIDExclude" access="readWrite">
			<syntax>
				<boolean />
				<default value="false" />
			</syntax>
		</parameter>
		<parameter name="SourceVendorClassID" access="readWrite">
			<syntax>
				<string>
					<size minLength="0" maxLength="255" />
				</string>
				<default value="" />
			</syntax>
		</parameter>
		<parameter name="SourceVendorClassIDExclude" access="readWrite">
			<syntax>
				<boolean />
				<default value="false" />
			</syntax>
		</parameter>
		<parameter name="SourceVendorClassIDMode" access="readWrite">
			<syntax>
				<string>
					<enumeration value="Exact" />
					<enumeration value="Prefix" />
					<enumeration value="Suffix" />
					<enumeration value="Substring" />
				</string>
				<default value="Exact" />
			</syntax>
		</parameter>
		<parameter name="SourceVendorClassIDv6" access="readWrite" supported="no">
			<syntax>
				<default value="" />
			</syntax>
		</parameter>
		<parameter name="SourceVendorSpecificInfo" access="readWrite" supported="no">
			<syntax>
				<default value="" />
			</syntax>
		</parameter>
		<parameter name="SourceVendorSpecificInfoEnterprise" access="readWrite" supported="no">
			<syntax>
				<unsignedInt />
				<default value="0" />
			</syntax>
		</parameter>
		<parameter name="SourceVendorSpecificInfoExclude" access="readWrite" supported="no">
			<syntax>
				<boolean />
				<default value="false" />
			</syntax>
		</parameter>
		<parameter name="SourceVendorSpecificInfoSubOption" access="readWrite" supported="no">
			<syntax>
				<int>
					<range minInclusive="0" maxInclusive="255" step="1" />
				</int>
				<default value="0" />
			</syntax>
		</parameter>
		<parameter name="Status" access="readOnly" store="no">
			<syntax>
				<string>
					<enumeration value="Disabled" />
					<enumeration value="Enabled" />
					<enumeration value="Error_Misconfigured" />
					<enumeration value="Error" />
				</string>
				<default value="Disabled" />
			</syntax>
		</parameter>
		<parameter name="TCPACK" access="readWrite">
			<syntax>
				<boolean />
				<default value="false" />
			</syntax>
		</parameter>
		<parameter name="TCPACKExclude" access="readWrite">
			<syntax>
				<boolean />
				<default value="false" />
			</syntax>
		</parameter>
		<parameter name="TrafficClass" access="readWrite">
			<syntax>
				<int>
					<range minInclusive="-1" step="1" />
				</int>
				<default value="-1" />
			</syntax>
		</parameter>
		<parameter name="VLANIDCheck" access="readWrite">
			<syntax>
				<int>
					<range minInclusive="-1" step="1" maxInclusive="4094" />
				</int>
				<default value="-1" />
			</syntax>
		</parameter>
		<parameter name="VLANIDExclude" access="readWrite">
			<syntax>
				<boolean />
				<default value="false" />
			</syntax>
		</parameter>
		<parameter name="X_ADB_ConnectionRateLimit" access="readWrite">
			<syntax>
				<int>
					<range minInclusive="0" maxInclusive="9999" step="1" />
				</int>
				<default value="0" />
			</syntax>
		</parameter>
		<parameter name="X_ADB_ConnectionRateLimitUnit" access="readWrite">
			<syntax>
				<string>
					<enumeration value="Seconds" />
					<enumeration value="Minutes" />
					<enumeration value="Hours" />
					<enumeration value="Days" />
				</string>
				<default value="Seconds" />
			</syntax>
		</parameter>
		<parameter name="X_ADB_ConnectionRateLimitBurst" access="readWrite">
			<syntax>
				<int>
					<range minInclusive="1" maxInclusive="9999" step="1" />
				</int>
				<default value="5" />
			</syntax>
		</parameter>
		<parameter name="X_ADB_DateStart" access="readWrite">
			<syntax>
				<dateTime />
				<default value="" />
			</syntax>
		</parameter>
		<parameter name="X_ADB_DateStop" access="readWrite">
			<syntax>
				<dateTime />
				<default value="" />
			</syntax>
		</parameter>
		<parameter name="X_ADB_NfMarkCheck" access="readWrite">
			<syntax>
				<int>
					<range minInclusive="-1" maxInclusive="255" step="1" />
				</int>
				<default value="-1" />
			</syntax>
		</parameter>
		<parameter name="X_ADB_NfMarkExclude" access="readWrite">
			<syntax>
				<boolean />
				<default value="false" />
			</syntax>
		</parameter>
		<parameter name="X_ADB_TimeStart" access="readWrite">
			<syntax>
				<string>
					<pattern value="" />
					<pattern value="[0-2][0-9]:[0-5][0-9](:[0-5][0-9])?" />
				</string>
				<default value="" />
			</syntax>
		</parameter>
		<parameter name="X_ADB_TimeStop" access="readWrite">
			<syntax>
				<string>
					<pattern value="" />
					<pattern value="[0-2][0-9]:[0-5][0-9](:[0-5][0-9])?" />
				</string>
				<default value="" />
			</syntax>
		</parameter>
		<parameter name="X_ADB_MonthDays" access="readWrite">
			<syntax>
				<list minItems="0" maxItems="31" />
				<unsignedInt>
					<range minInclusive="1" maxInclusive="31" step="1" />
				</unsignedInt>
				<default value="" />
			</syntax>
		</parameter>
		<parameter name="X_ADB_WeekDays" access="readWrite">
			<syntax>
				<list minItems="0" maxItems="7" />
				<unsignedInt>
					<range minInclusive="1" maxInclusive="7" step="1" />
				</unsignedInt>
				<default value="" />
			</syntax>
		</parameter>
		<parameter name="X_ADB_ExtraDestPorts" access="readWrite">
			<syntax>
				<list minItems="0" maxItems="15" />
				<string>
					<pattern value="((6553[0-5]|655[0-2][0-9]|65[0-4][0-9][0-9]|6[0-4][0-9][0-9][0-9]|[1-5][0-9][0-9][0-9][0-9]|[1-9][0-9]{0,3})(:(6553[0-5]|655[0-2][0-9]|65[0-4][0-9][0-9]|6[0-4][0-9][0-9][0-9]|[1-5][0-9][0-9][0-9][0-9]|[1-9][0-9]{0,3}))?)" />
				</string>
				<default value="" />
			</syntax>
		</parameter>
		<parameter name="X_ADB_ExtraSourcePorts" access="readWrite">
			<syntax>
				<list minItems="0" maxItems="15" />
				<string>
					<pattern value="((6553[0-5]|655[0-2][0-9]|65[0-4][0-9][0-9]|6[0-4][0-9][0-9][0-9]|[1-5][0-9][0-9][0-9][0-9]|[1-9][0-9]{0,3})(:(6553[0-5]|655[0-2][0-9]|65[0-4][0-9][0-9]|6[0-4][0-9][0-9][0-9]|[1-5][0-9][0-9][0-9][0-9]|[1-9][0-9]{0,3}))?)" />
				</string>
				<default value="" />
			</syntax>
		</parameter>
		<parameter name="X_ADB_Permissions" access="readWrite">
			<syntax>
				<dataType ref="UserPermission" />
				<default value="333" />
			</syntax>
		</parameter>
	</object>
	<object name="QoS.Flow.{i}." access="readWrite" minEntries="0" maxEntries="unbounded" numEntriesParameter="FlowNumberOfEntries" enableParameter="Enable" set="QoSFlow.sh" del="QoSFlow.sh,Yatta.sh">
		<parameter name="Alias" access="readWrite" key="yes">
			<syntax>
				<dataType ref="Alias" />
			</syntax>
		</parameter>
		<parameter name="App" access="readWrite" set="Yatta.sh">
			<syntax>
				<string>
					<size minLength="0" maxLength="256" />
					<pathRef targetParent="#.App." refType="strong" targetType="row" />
				</string>
				<default value="" />
			</syntax>
		</parameter>
		<parameter name="DSCPMark" access="readWrite">
			<syntax>
				<int>
					<range minInclusive="-2" step="1" />
				</int>
				<default value="-1" />
			</syntax>
		</parameter>
		<parameter name="Enable" access="readWrite" set="Yatta.sh">
			<syntax>
				<boolean />
				<default value="false" />
			</syntax>
		</parameter>
		<parameter name="EthernetPriorityMark" access="readWrite">
			<syntax>
				<int>
					<range minInclusive="-2" step="1" />
				</int>
				<default value="-1" />
			</syntax>
		</parameter>
		<parameter name="ForwardingPolicy" access="readWrite">
			<syntax>
				<unsignedInt />
				<default value="0" />
			</syntax>
		</parameter>
		<parameter name="Name" access="readWrite">
			<syntax>
				<dataType ref="Name" />
			</syntax>
		</parameter>
		<parameter name="Policer" access="readWrite">
			<syntax>
				<string>
					<size minLength="0" maxLength="256" />
					<pathRef targetParent="#.Policer." refType="strong" targetType="row" />
				</string>
				<default value="" />
			</syntax>
		</parameter>
		<parameter name="Status" access="readOnly" store="no">
			<syntax>
				<string>
					<enumeration value="Disabled" />
					<enumeration value="Enabled" />
					<enumeration value="Error" />
				</string>
				<default value="Disabled" />
			</syntax>
		</parameter>
		<parameter name="TrafficClass" access="readWrite">
			<syntax>
				<unsignedInt />
				<default value="0" />
			</syntax>
		</parameter>
		<parameter name="Type" access="readWrite">
			<syntax>
				<string>
					<size minLength="0" maxLength="256" />
				</string>
				<default value="" />
			</syntax>
		</parameter>
		<parameter name="TypeParameters" access="readWrite" supported="no">
			<syntax>
				<string>
					<size minLength="0" maxLength="256" />
				</string>
				<default value="" />
			</syntax>
		</parameter>
		<parameter name="X_ADB_Permissions" access="readWrite">
			<syntax>
				<dataType ref="UserPermission" />
				<default value="333" />
			</syntax>
		</parameter>
	</object>
	<object name="QoS.Policer.{i}." access="readWrite" minEntries="0" maxEntries="unbounded" numEntriesParameter="PolicerNumberOfEntries" enableParameter="Enable" set="QoSPolicer.sh" add="QoSPolicer.sh" del="QoSPolicer.sh">
		<parameter name="Alias" access="readWrite" key="yes">
			<syntax>
				<dataType ref="Alias" />
			</syntax>
		</parameter>
		<parameter name="CommittedBurstSize" access="readWrite">
			<syntax>
				<unsignedInt />
				<default value="0" />
			</syntax>
		</parameter>
		<parameter name="CommittedRate" access="readWrite">
			<syntax>
				<unsignedInt>
					<units value="bits per second" />
				</unsignedInt>
				<default value="0" />
			</syntax>
		</parameter>
		<parameter name="ConformingAction" access="readWrite">
			<syntax>
				<string>
					<pattern value="Null" />
					<pattern value="Drop" />
					<pattern value="[0-9]|[1-5][0-9]|6[0-3]" />
					<pattern value=":[0-7]" />
					<pattern value="([0-9]|[1-5][0-9]|6[0-3]):[0-7]" />
				</string>
				<default value="Null" />
			</syntax>
		</parameter>
		<parameter name="ConformingCountedBytes" access="readOnly" activeNotify="canDeny" get="QoSPolicer.sh" store="no">
			<syntax>
				<unsignedInt />
				<default value="0" />
			</syntax>
		</parameter>
		<parameter name="ConformingCountedPackets" access="readOnly" activeNotify="canDeny" get="QoSPolicer.sh" store="no">
			<syntax>
				<unsignedInt />
				<default value="0" />
			</syntax>
		</parameter>
		<parameter name="Enable" access="readWrite">
			<syntax>
				<boolean />
				<default value="false" />
			</syntax>
		</parameter>
		<parameter name="ExcessBurstSize" access="readWrite">
			<syntax>
				<unsignedInt />
				<default value="0" />
			</syntax>
		</parameter>
		<parameter name="MeterType" access="readWrite">
			<syntax>
				<string>
					<enumerationRef targetParam="PossibleMeterTypes" />
				</string>
				<default value="SimpleTokenBucket" />
			</syntax>
		</parameter>
		<parameter name="NonConformingAction" access="readWrite">
			<syntax>
				<string>
					<pattern value="Null" />
					<pattern value="Drop" />
					<pattern value="[0-9]|[1-5][0-9]|6[0-3]" />
					<pattern value=":[0-7]" />
					<pattern value="([0-9]|[1-5][0-9]|6[0-3]):[0-7]" />
				</string>
				<default value="Drop" />
			</syntax>
		</parameter>
		<parameter name="NonConformingCountedBytes" access="readOnly" activeNotify="canDeny" get="QoSPolicer.sh" store="no">
			<syntax>
				<unsignedInt />
				<default value="0" />
			</syntax>
		</parameter>
		<parameter name="NonConformingCountedPackets" access="readOnly" activeNotify="canDeny" get="QoSPolicer.sh" store="no">
			<syntax>
				<unsignedInt />
				<default value="0" />
			</syntax>
		</parameter>
		<parameter name="PartialConformingAction" access="readWrite">
			<syntax>
				<string>
					<pattern value="Null" />
					<pattern value="Drop" />
					<pattern value="[0-9]|[1-5][0-9]|6[0-3]" />
					<pattern value=":[0-7]" />
					<pattern value="([0-9]|[1-5][0-9]|6[0-3]):[0-7]" />
				</string>
				<default value="Drop" />
			</syntax>
		</parameter>
		<parameter name="PartiallyConformingCountedBytes" access="readOnly" activeNotify="canDeny" get="QoSPolicer.sh" store="no">
			<syntax>
				<unsignedInt />
				<default value="0" />
			</syntax>
		</parameter>
		<parameter name="PartiallyConformingCountedPackets" access="readOnly" activeNotify="canDeny" get="QoSPolicer.sh" store="no">
			<syntax>
				<unsignedInt />
				<default value="0" />
			</syntax>
		</parameter>
		<parameter name="PeakBurstSize" access="readWrite">
			<syntax>
				<unsignedInt />
				<default value="0" />
			</syntax>
		</parameter>
		<parameter name="PeakRate" access="readWrite">
			<syntax>
				<unsignedInt>
					<units value="bits per second" />
				</unsignedInt>
				<default value="0" />
			</syntax>
		</parameter>
		<parameter name="PossibleMeterTypes" access="readOnly" activeNotify="canDeny">
			<syntax>
				<list />
				<string>
					<enumeration value="SimpleTokenBucket" />
					<enumeration value="SingleRateThreeColor" />
					<enumeration value="TwoRateThreeColor" />
				</string>
				<default value="SimpleTokenBucket,SingleRateThreeColor,TwoRateThreeColor" />
			</syntax>
		</parameter>
		<parameter name="Status" access="readOnly" store="no">
			<syntax>
				<string>
					<enumeration value="Disabled" />
					<enumeration value="Enabled" />
					<enumeration value="Error" />
				</string>
				<default value="Disabled" />
			</syntax>
		</parameter>
		<parameter name="TotalCountedBytes" access="readOnly" activeNotify="canDeny" get="QoSPolicer.sh" store="no">
			<syntax>
				<unsignedInt />
				<default value="0" />
			</syntax>
		</parameter>
		<parameter name="TotalCountedPackets" access="readOnly" activeNotify="canDeny" get="QoSPolicer.sh" store="no">
			<syntax>
				<unsignedInt />
				<default value="0" />
			</syntax>
		</parameter>
	</object>
	<object name="QoS.Queue.{i}." access="readWrite" minEntries="0" maxEntries="unbounded" numEntriesParameter="QueueNumberOfEntries" enableParameter="Enable" set="QoSQueue.sh" add="QoSQueue.sh" del="QoSQueue.sh">
		<parameter name="Alias" access="readWrite" key="yes">
			<syntax>
				<dataType ref="Alias" />
			</syntax>
		</parameter>
		<parameter name="AllInterfaces" access="readWrite">
			<syntax>
				<boolean />
				<default value="false" />
			</syntax>
		</parameter>
		<parameter name="BufferLength" access="readOnly" get="QoSQueueStats.sh" store="no">
			<syntax>
				<unsignedInt />
			</syntax>
		</parameter>
		<parameter name="DropAlgorithm" access="readWrite">
			<syntax>
				<string>
					<enumeration value="RED" />
					<enumeration value="DT" />
				</string>
				<default value="DT" />
			</syntax>
		</parameter>
		<parameter name="Enable" access="readWrite">
			<syntax>
				<boolean />
				<default value="false" />
			</syntax>
		</parameter>
		<parameter name="HardwareAssisted" access="readOnly">
			<syntax>
				<boolean />
				<default value="false" />
			</syntax>
		</parameter>
		<parameter name="Interface" access="readWrite">
			<syntax>
				<string>
					<size minLength="0" maxLength="256" />
					<pathRef refType="strong" targetType="row" />
				</string>
				<default value="" />
			</syntax>
		</parameter>
		<parameter name="Precedence" access="readWrite">
			<syntax>
				<unsignedInt>
					<range minInclusive="1" step="1" />
				</unsignedInt>
				<default value="1" />
			</syntax>
		</parameter>
		<parameter name="REDPercentage" access="readWrite">
			<syntax>
				<unsignedInt>
					<range maxInclusive="100" step="1" />
				</unsignedInt>
				<default value="0" />
			</syntax>
		</parameter>
		<parameter name="REDThreshold" access="readWrite">
			<syntax>
				<unsignedInt>
					<range maxInclusive="100" step="1" />
				</unsignedInt>
				<default value="0" />
			</syntax>
		</parameter>
		<parameter name="SchedulerAlgorithm" access="readWrite">
			<syntax>
				<string>
					<enumeration value="WFQ" />
					<enumeration value="WRR" />
					<enumeration value="SP" />
				</string>
				<default value="SP" />
			</syntax>
		</parameter>
		<parameter name="ShapingBurstSize" access="readWrite">
			<syntax>
				<unsignedInt />
				<default value="0" />
			</syntax>
		</parameter>
		<parameter name="ShapingRate" access="readWrite">
			<syntax>
				<int>
					<range minInclusive="-1" step="1" />
				</int>
				<default value="-1" />
			</syntax>
		</parameter>
		<parameter name="Status" access="readOnly" store="no">
			<syntax>
				<string>
					<enumeration value="Disabled" />
					<enumeration value="Enabled" />
					<enumeration value="Error_Misconfigured" />
					<enumeration value="Error" />
				</string>
				<default value="Disabled" />
			</syntax>
		</parameter>
		<parameter name="TrafficClasses" access="readWrite">
			<syntax>
				<list>
					<size minLength="0" maxLength="256" />
				</list>
				<unsignedInt />
				<default value="" />
			</syntax>
		</parameter>
		<parameter name="Weight" access="readWrite">
			<syntax>
				<unsignedInt />
				<default value="0" />
			</syntax>
		</parameter>
		<parameter name="X_ADB_Parent" access="readWrite">
			<syntax>
				<string>
					<size minLength="0" maxLength="256" />
					<pathRef targetParent=".QoS.Queue." refType="strong" targetType="row" />
				</string>
				<default value="" />
			</syntax>
		</parameter>
		<parameter name="X_ADB_TargetLatency" access="readWrite">
			<syntax>
				<unsignedInt>
					<range minInclusive="1" maxInclusive="100000" step="1" />
					<units value="milliseconds" />
				</unsignedInt>
				<default value="250" />
			</syntax>
		</parameter>
		<parameter name="X_ADB_Handle" access="readOnly" store="no">
			<syntax>
				<string>
					<size minLength="0" maxLength="64" />
				</string>
			</syntax>
		</parameter>
		<parameter name="X_ADB_Permissions" access="readWrite">
			<syntax>
				<dataType ref="UserPermission" />
				<default value="333" />
			</syntax>
		</parameter>
	</object>
	<object name="QoS.QueueStats.{i}." access="readWrite" minEntries="0" maxEntries="unbounded" numEntriesParameter="QueueStatsNumberOfEntries" enableParameter="Enable" set="QoSQueueStats.sh">
		<parameter name="Alias" access="readWrite" key="yes">
			<syntax>
				<dataType ref="Alias" />
			</syntax>
		</parameter>
		<parameter name="DroppedBytes" access="readOnly" activeNotify="canDeny" get="QoSQueueStats.sh" store="no">
			<syntax>
				<unsignedInt />
				<default value="0" />
			</syntax>
		</parameter>
		<parameter name="DroppedPackets" access="readOnly" activeNotify="canDeny" get="QoSQueueStats.sh" store="no">
			<syntax>
				<unsignedInt />
				<default value="0" />
			</syntax>
		</parameter>
		<parameter name="Enable" access="readWrite">
			<syntax>
				<boolean />
				<default value="false" />
			</syntax>
		</parameter>
		<parameter name="Interface" access="readWrite">
			<syntax>
				<string>
					<size minLength="0" maxLength="256" />
					<pathRef refType="strong" targetType="row" />
				</string>
				<default value="" />
			</syntax>
		</parameter>
		<parameter name="OutputBytes" access="readOnly" activeNotify="canDeny" get="QoSQueueStats.sh" store="no">
			<syntax>
				<unsignedInt />
				<default value="0" />
			</syntax>
		</parameter>
		<parameter name="OutputPackets" access="readOnly" activeNotify="canDeny" get="QoSQueueStats.sh" store="no">
			<syntax>
				<unsignedInt />
				<default value="0" />
			</syntax>
		</parameter>
		<parameter name="Queue" access="readWrite">
			<syntax>
				<string>
					<size minLength="0" maxLength="256" />
					<pathRef targetParent="#.Queue." refType="strong" targetType="row" />
				</string>
				<default value="" />
			</syntax>
		</parameter>
		<parameter name="QueueOccupancyPackets" access="readOnly" activeNotify="canDeny" get="QoSQueueStats.sh" store="no">
			<syntax>
				<unsignedInt />
				<default value="0" />
			</syntax>
		</parameter>
		<parameter name="QueueOccupancyPercentage" access="readOnly" activeNotify="canDeny" get="QoSQueueStats.sh" store="no">
			<syntax>
				<unsignedInt>
					<range minInclusive="0" maxInclusive="100" step="1" />
					<units value="percent" />
				</unsignedInt>
				<default value="0" />
			</syntax>
		</parameter>
		<parameter name="Status" access="readOnly">
			<syntax>
				<string>
					<enumeration value="Disabled" />
					<enumeration value="Enabled" />
					<enumeration value="Error" />
				</string>
				<default value="Disabled" />
			</syntax>
		</parameter>
	</object>
	<object name="QoS.X_ADB_IngressShaper.{i}." access="readWrite" minEntries="0" maxEntries="unbounded" numEntriesParameter="IngressShaperNumberOfEntries" enableParameter="Enable" set="QoSIngressShaper.sh" del="QoSIngressShaper.sh">
		<parameter name="Alias" access="readWrite" key="yes">
			<syntax>
				<dataType ref="Alias" />
			</syntax>
		</parameter>
		<parameter name="Enable" access="readWrite">
			<syntax>
				<boolean />
				<default value="false" />
			</syntax>
		</parameter>
		<parameter name="Interface" access="readWrite">
			<syntax>
				<string>
					<size minLength="0" maxLength="256" />
					<pathRef refType="strong" targetType="row" />
				</string>
				<default value="" />
			</syntax>
		</parameter>
		<parameter name="ShapingBurstSize" access="readWrite">
			<syntax>
				<unsignedInt />
				<default value="0" />
			</syntax>
		</parameter>
		<parameter name="ShapingRate" access="readWrite">
			<syntax>
				<int>
					<range minInclusive="-1" step="1" />
				</int>
				<default value="-1" />
			</syntax>
		</parameter>
		<parameter name="Status" access="readOnly" store="no">
			<syntax>
				<string>
					<enumeration value="Disabled" />
					<enumeration value="Enabled" />
					<enumeration value="Error_Misconfigured" />
					<enumeration value="Error" />
				</string>
				<default value="Disabled" />
			</syntax>
		</parameter>
	</object>
	<object name="QoS.Shaper.{i}." access="readWrite" minEntries="0" maxEntries="unbounded" numEntriesParameter="ShaperNumberOfEntries" enableParameter="Enable" set="QoSQueue.sh" add="QoSQueue.sh" del="QoSQueue.sh">
		<parameter name="Alias" access="readWrite" key="yes">
			<syntax>
				<dataType ref="Alias" />
			</syntax>
		</parameter>
		<parameter name="Enable" access="readWrite">
			<syntax>
				<boolean />
				<default value="false" />
			</syntax>
		</parameter>
		<parameter name="Interface" access="readWrite">
			<syntax>
				<string>
					<size minLength="0" maxLength="256" />
					<pathRef refType="strong" targetType="row" />
				</string>
				<default value="" />
			</syntax>
		</parameter>
		<parameter name="ShapingBurstSize" access="readWrite">
			<syntax>
				<unsignedInt />
				<default value="0" />
			</syntax>
		</parameter>
		<parameter name="ShapingRate" access="readWrite">
			<syntax>
				<int>
					<range minInclusive="-1" step="1" />
				</int>
				<default value="-1" />
			</syntax>
		</parameter>
		<parameter name="Status" access="readOnly" store="no">
			<syntax>
				<string>
					<enumeration value="Disabled" />
					<enumeration value="Enabled" />
					<enumeration value="Error_Misconfigured" />
					<enumeration value="Error" />
				</string>
				<default value="Disabled" />
			</syntax>
		</parameter>
		<parameter name="X_ADB_Permissions" access="readWrite">
			<syntax>
				<dataType ref="UserPermission" />
				<default value="333" />
			</syntax>
		</parameter>
	</object>
	<object name="Routing.Router.{i}.IPv4Forwarding.{i}." access="readWrite" minEntries="0" maxEntries="unbounded" numEntriesParameter="IPv4ForwardingNumberOfEntries" enableParameter="Enable" set="RoutingRouterIPv4.sh" del="RoutingRouterIPv4.sh">
		<parameter name="ForwardingPolicy" access="readWrite">
			<syntax>
				<int>
					<range minInclusive="-1" step="1" />
				</int>
				<default value="-1" />
			</syntax>
		</parameter>
		<parameter name="X_ADB_ForwardingPolicyMask" access="readWrite">
			<syntax>
				<unsignedInt>
					<range minInclusive="0" maxInclusive="255" step="1" />
				</unsignedInt>
				<default value="255" />
			</syntax>
		</parameter>
	</object>
	<object name="Routing.Router.{i}.IPv6Forwarding.{i}." access="readWrite" minEntries="0" maxEntries="unbounded" numEntriesParameter="IPv6ForwardingNumberOfEntries" enableParameter="Enable">
		<parameter name="ForwardingPolicy" access="readWrite">
			<syntax>
				<int>
					<range minInclusive="-1" step="1" />
				</int>
				<default value="-1" />
			</syntax>
		</parameter>
	</object>
	<object name="DSL.Line.{i}.X_ADB_HwBasedQos." access="readOnly" minEntries="1" maxEntries="1">
		<parameter name="Capable" access="readOnly" activeNotify="canDeny">
			<syntax>
				<boolean />
				<default value="false" />
			</syntax>
		</parameter>
		<parameter name="Enable" access="readWrite" set="QoSQueue.sh">
			<syntax>
				<boolean />
				<default value="false" />
			</syntax>
		</parameter>
		<parameter name="Status" access="readOnly" store="no">
			<syntax>
				<string>
					<enumeration value="Enabled" />
					<enumeration value="Disabled" />
				</string>
				<default value="Disabled" />
			</syntax>
		</parameter>
	</object>
	<object name="Ethernet.Interface.{i}.X_ADB_HwBasedQos." access="readOnly" minEntries="1" maxEntries="1">
		<parameter name="Capable" access="readOnly" activeNotify="canDeny">
			<syntax>
				<boolean />
				<default value="false" />
			</syntax>
		</parameter>
		<parameter name="Enable" access="readWrite" set="QoSQueue.sh">
			<syntax>
				<boolean />
				<default value="false" />
			</syntax>
		</parameter>
		<parameter name="Status" access="readOnly" store="no">
			<syntax>
				<string>
					<enumeration value="Enabled" />
					<enumeration value="Disabled" />
				</string>
				<default value="Disabled" />
			</syntax>
		</parameter>
	</object>
	<object name="WiFi.SSID.{i}.X_ADB_HwBasedQos." access="readOnly" minEntries="1" maxEntries="1">
		<parameter name="Capable" access="readOnly" activeNotify="canDeny">
			<syntax>
				<boolean />
				<default value="false" />
			</syntax>
		</parameter>
		<parameter name="Enable" access="readWrite" set="QoSQueue.sh">
			<syntax>
				<boolean />
				<default value="false" />
			</syntax>
		</parameter>
		<parameter name="Status" access="readOnly" store="no">
			<syntax>
				<string>
					<enumeration value="Enabled" />
					<enumeration value="Disabled" />
				</string>
				<default value="Disabled" />
			</syntax>
		</parameter>
	</object>
</datamodel>
